{"is_source_file": true, "format": "JavaScript (React JSX)", "description": "This file defines a React functional component called 'Footer' that renders a footer element with the current year and some styling.", "external_files": ["./Footer.css"], "external_methods": [], "published": ["default"], "classes": [], "methods": [{"name": "Footer()", "description": "React functional component rendering the application's footer.", "scope": "", "scopeKind": ""}], "calls": ["React"], "search-terms": ["React", "Footer", "Footer.js", "React component", "footer"], "state": 2, "file_id": 15, "knowledge_revision": 32, "git_revision": "", "ctags": [{"_type": "tag", "name": "Footer", "path": "/home/kavia/workspace/code-generation/user-request-test-project-86711f5a/frontend_web_app/src/components/Footer.js", "pattern": "/^function Footer() {$/", "language": "JavaScript", "kind": "function", "signature": "()"}], "hash": "b7730014e7b8cc719092a5fe3152cb65", "format-version": 4, "code-base-name": "frontend_web_app", "filename": "frontend_web_app/src/components/Footer.js", "revision_history": [{"32": ""}]}